botnium/__init__.py
botnium/element.py
botnium/.locator/common.cnstore
botnium/.locator/common_img/272791d8-64ce-41ff-8915-b28c409344e2.jpg
botnium/.locator/common_img/368ef69c-7a71-4e23-8e4a-0cc6ea0d3e17.jpg
botnium/.locator/common_img/58ddb9e1-3e31-4bae-a5a0-9545a412d054.jpg
botnium/.locator/common_img/647b731e-7253-4284-881e-7296d3e1cab6.jpg
botnium/.locator/common_img/6a9f29de-e376-4106-a792-77cec8930529.jpg
botnium/.locator/common_img/6ba9c406-aab9-4a81-bef5-698c181b7f1e.jpg
botnium/.locator/common_img/be3a55dd-8594-434d-b90b-d3a5fed9880e.jpg
botnium/.locator/common_img/c0a149d3-71a7-43fd-9e36-453acac8712d.jpg
botnium/.locator/common_img/c8974736-dfc7-4268-872c-fd0f01a98bf2.jpg
botnium/.locator/common_img/fc652ec2-c1c7-4f89-b3fd-7b1cc51b5b3e.jpg
botnium/common/__init__.py
botnium/common/models.py
botnium/common/toolkit.py
botnium/common/utils.py
botnium/lib/CSharpRPA.dll
botnium/lib/KeyboardCollection.dll
botnium/lib/OpenCvSharp.dll
botnium/lib/lib/AutoKeyBoard.dll
botnium/lib/lib/DD32.dll
botnium/lib/lib/DD64.dll
botnium/lib/lib/DD96699.32.dll
botnium/lib/lib/DD96699.32.x.dll
botnium/lib/lib/DD96699.64.dll
botnium/lib/lib/DD96699.64.x.dll
botnium/lib/lib/DDHID32.dll
botnium/lib/lib/DDHID32_1.dll
botnium/lib/lib/DDHID64.dll
botnium/lib/lib/DDHID64_1.dll
botnium/lib/lib/WinRing0.dll
botnium/lib/lib/WinRing0.sys
botnium/lib/lib/WinRing0x64.dll
botnium/lib/lib/WinRing0x64.sys
botnium/logger/__init__.py
botnium-1.0.7.dist-info/METADATA
botnium-1.0.7.dist-info/WHEEL
botnium-1.0.7.dist-info/top_level.txt
botnium-1.0.7.dist-info/RECORD
