Metadata-Version: 2.1
Name: botnium
Version: 1.0.7
Summary: Python toolkits for RPA projects.
Home-page: https://www.botnium.com
Author: QCYQ
Author-email: devadmin@botnium.com
Project-URL: Documentation, https://www.botnium.com
Classifier: Environment :: Win32 (MS Windows)
Classifier: Programming Language :: Python :: 3.7
Classifier: Programming Language :: Python :: 3.8
Classifier: Programming Language :: Python :: 3.9
Classifier: Programming Language :: Python :: 3.10
Classifier: License :: OSI Approved :: Apache Software License
Classifier: Operating System :: Microsoft :: Windows
Requires-Dist: pythonnet
Requires-Dist: typing-extensions
